thrift_parser/README.md
thrift_parser/Thrift.interp
thrift_parser/Thrift.tokens
thrift_parser/ThriftLexer.interp
thrift_parser/ThriftLexer.py
thrift_parser/ThriftLexer.tokens
thrift_parser/ThriftListener.py
thrift_parser/ThriftParser.py
thrift_parser/__init__.py
thrift_parser/parse.py
thrift_parser-1.0.7.dist-info/WHEEL
thrift_parser-1.0.7.dist-info/METADATA
thrift_parser-1.0.7.dist-info/RECORD
