Metadata-Version: 2.1
Name: thrift-parser
Version: 1.0.7
Summary: a thrift parser (antlr4)
License: MIT
Author-email: alingse <alingse@foxmail.com>
Requires-Python: >=3.7
Requires-Dist: antlr4-python3-runtime==4.11.1
